odoo10_addon_l10n_it_pec-10.0.1.0.0-py2.7-nspkg.pth
odoo/addons/l10n_it_pec/__manifest__.py
odoo/addons/l10n_it_pec/__init__.py
odoo/addons/l10n_it_pec/README.rst
odoo/addons/l10n_it_pec/models/partner.py
odoo/addons/l10n_it_pec/models/__init__.py
odoo/addons/l10n_it_pec/i18n/it.po
odoo/addons/l10n_it_pec/i18n/es.po
odoo/addons/l10n_it_pec/i18n/sl.po
odoo/addons/l10n_it_pec/views/partner_view.xml
odoo/addons/l10n_it_pec/static/description/icon.png
odoo10_addon_l10n_it_pec-10.0.1.0.0.dist-info/top_level.txt
odoo10_addon_l10n_it_pec-10.0.1.0.0.dist-info/WHEEL
odoo10_addon_l10n_it_pec-10.0.1.0.0.dist-info/RECORD
odoo10_addon_l10n_it_pec-10.0.1.0.0.dist-info/metadata.json
odoo10_addon_l10n_it_pec-10.0.1.0.0.dist-info/DESCRIPTION.rst
odoo10_addon_l10n_it_pec-10.0.1.0.0.dist-info/METADATA
odoo10_addon_l10n_it_pec-10.0.1.0.0.dist-info/namespace_packages.txt
